data4co/__init__.py
data4co/data/__init__.py
data4co/data/mis/__init__.py
data4co/data/mis/satlib.py
data4co/data/tsp/__init__.py
data4co/data/tsp/tsp_uniform.py
data4co/data/tsp/tsplib_origin.py
data4co/draw/mis.py
data4co/draw/tsp.py
data4co/draw/utils.py
data4co/evaluate/__init__.py
data4co/evaluate/mis/__init__.py
data4co/evaluate/mis/satlib_eva.py
data4co/evaluate/tsp/__init__.py
data4co/evaluate/tsp/base.py
data4co/evaluate/tsp/tsplib_origin_eva.py
data4co/evaluate/tsp/uniform_eva.py
data4co/generator/__init__.py
data4co/generator/mis_data.py
data4co/generator/tsp_data.py
data4co/solver/__init__.py
data4co/solver/mis/__init__.py
data4co/solver/mis/base.py
data4co/solver/mis/gurobi.py
data4co/solver/mis/kamis.py
data4co/solver/mis/KaMIS/deploy/graphchecker
data4co/solver/mis/KaMIS/deploy/online_mis
data4co/solver/mis/KaMIS/deploy/redumis
data4co/solver/mis/KaMIS/deploy/sort_adjacencies
data4co/solver/mis/KaMIS/deploy/weighted_branch_reduce
data4co/solver/mis/KaMIS/deploy/weighted_local_search
data4co/solver/mis/kamis-source/CMakeLists.txt
data4co/solver/mis/kamis-source/Doxyfile
data4co/solver/mis/kamis-source/cleanup.sh
data4co/solver/mis/kamis-source/compile_withcmake.sh
data4co/solver/mis/kamis-source/app/configuration_mis.h
data4co/solver/mis/kamis-source/app/graphchecker.cpp
data4co/solver/mis/kamis-source/app/online_mis.cpp
data4co/solver/mis/kamis-source/app/parse_parameters.h
data4co/solver/mis/kamis-source/app/parse_parameters_omis.h
data4co/solver/mis/kamis-source/app/reduction_evomis.cpp
data4co/solver/mis/kamis-source/app/sort_adjacencies.cpp
data4co/solver/mis/kamis-source/extern/KaHIP/app/balance_configuration.h
data4co/solver/mis/kamis-source/extern/KaHIP/app/configuration.h
data4co/solver/mis/kamis-source/extern/KaHIP/interface/SConscript
data4co/solver/mis/kamis-source/extern/KaHIP/interface/SConstruct
data4co/solver/mis/kamis-source/extern/KaHIP/interface/kaHIP_interface.cpp
data4co-0.0.1a19.dist-info/METADATA
data4co-0.0.1a19.dist-info/WHEEL
data4co-0.0.1a19.dist-info/top_level.txt
data4co-0.0.1a19.dist-info/RECORD
