Metadata-Version: 2.1
Name: data4co
Version: 0.0.1a19
Summary: data4co provides convenient dataset generators for the combinatorial optimization problem
Home-page: https://github.com/heatingma/Data4CO
Author: ThinkLab at SJTU
License: Mulan PSL v2
Classifier: License :: OSI Approved :: Mulan Permissive Software License v2 (MulanPSL-2.0)
Classifier: Programming Language :: Python
Classifier: Programming Language :: Python :: 3
Classifier: Programming Language :: Python :: 3.8
Classifier: Programming Language :: Python :: 3.9
Classifier: Programming Language :: Python :: 3.10
Classifier: Programming Language :: Python :: 3 :: Only
Classifier: Programming Language :: Python :: Implementation :: CPython
Classifier: Operating System :: Unix
Classifier: Environment :: Console
Classifier: Topic :: Scientific/Engineering :: Artificial Intelligence
Classifier: Topic :: Scientific/Engineering :: Image Recognition
Classifier: Topic :: Scientific/Engineering :: Mathematics
Requires-Python: >=3.8
Requires-Dist: numpy>=1.24.4
Requires-Dist: networkx>=2.8.8
Requires-Dist: tsplib95>=0.7.1
Requires-Dist: tqdm>=4.66.1
Requires-Dist: requests>=2.31.0
Requires-Dist: pulp>=2.8.0
Requires-Dist: pandas>=2.0.0
Requires-Dist: scipy>=1.10.1
Requires-Dist: aiohttp>=3.9.3
